mvbep/__init__.py
mvbep/__version__.py
mvbep/developer.py
mvbep/initializer.py
mvbep/interpreter.py
mvbep/mvbep.py
mvbep/towt_utils.py
mvbep/transformer.py
mvbep/writer.py
mvbep/templates/dev_temp.html
mvbep/templates/init_temp.html
mvbep/templates/quant_temp.html
mvbep-0.0.1.dist-info/LICENSE
mvbep-0.0.1.dist-info/METADATA
mvbep-0.0.1.dist-info/WHEEL
mvbep-0.0.1.dist-info/top_level.txt
mvbep-0.0.1.dist-info/RECORD
