Metadata-Version: 2.1
Name: mvbep
Version: 0.0.1
Summary: Measurement and Verification Building Energy Prediction (MVBEP) is an open-source framework for developing data-driven models for predicting the building baseline energy consumption and estimating savings associated with retrofitting in the post-retrofit period.
Author-email: Abdurahman Alrobaie <robaie98@outlook.com>
Project-URL: repository, https://github.com/Robaie98/mvbep
Project-URL: documentation, https://mvbep.readthedocs.io/en/latest/
Keywords: measurement and verification,building energy modeling,energy baseline
Classifier: License :: OSI Approved :: MIT License
Classifier: Programming Language :: Python
Requires-Python: >=3.6
License-File: LICENSE
Requires-Dist: holidays (>=0.14.2)
Requires-Dist: joblib (>=1.1.0)
Requires-Dist: numpy (>=1.20.3)
Requires-Dist: pandas (>=1.3.4)
Requires-Dist: plotly (>=5.7.0)
Requires-Dist: schema (==0.7.5)
Requires-Dist: scikit-learn (>=1.0.2)
Requires-Dist: shap (>=0.41.0)
Requires-Dist: statsmodels (>=0.12.2)
Requires-Dist: xgboost (>=1.6.0)
